{
  "cycle": 1,
  "timestamp": "2026-04-16T08:10:36.000Z",
  "decision": "PROCEED",
  "tasks": ["P0-DEADCODE-1-5", "P1-CONSTANTS-1-3", "TEST-BUGHUNT-1-2", "BUGFIX-CRITICAL-1-2", "INFRA-ROUTINE-1"],
  "rationale": "Cycle 1: diagnostic pipeline + dead code cleanup + constants v2.4 alignment + 2 critical bug fixes + autonomous infra setup. Next cycle: HIGH bug fixes (BUG-003,004,006,014) then TEST-PLAYTEST-1 + TEST-AUDIT-1.",
  "budget": {"files": 18, "lines": 1505},
  "blockers": [],
  "next_cycle_plan": "Fix remaining HIGH bugs (biome display names, effect format mismatch, randi_range, faction defaults). Then run playtest + bible audit."
}
